nous/__init__.py
nous/facts.py
nous/model.py
nous/prototypes.py
nous/types.py
nous/version.py
nous/data/__init__.py
nous/data/california.py
nous/data/wine.py
nous/explain/__init__.py
nous/explain/aggregator.py
nous/explain/cf.py
nous/explain/facts_desc.py
nous/explain/fidelity.py
nous/explain/generate.py
nous/explain/global_book.py
nous/explain/loo.py
nous/explain/mse.py
nous/explain/pruning.py
nous/explain/stability.py
nous/explain/traces.py
nous/explain/utils.py
nous/export/__init__.py
nous/export/numpy_infer.py
nous/optim/__init__.py
nous/optim/base.py
nous/optim/beta_ng.py
nous/optim/extragrad_trust.py
nous/optim/factory.py
nous/optim/mirror_radam.py
nous/optim/sam_gates.py
nous/rules/__init__.py
nous/rules/blocks.py
nous/rules/fixed.py
nous/rules/gaters.py
nous/rules/soft_fact.py
nous/rules/softmax.py
nous/rules/sparse.py
nous/training/__init__.py
nous/training/evaluation.py
nous/training/schedulers.py
nous/training/train.py
nous/utils/__init__.py
nous/utils/calibrators.py
nous/utils/metrics.py
nous/utils/seed.py
nous-0.5.1.dist-info/licenses/LICENSE
nous-0.5.1.dist-info/METADATA
nous-0.5.1.dist-info/WHEEL
nous-0.5.1.dist-info/top_level.txt
nous-0.5.1.dist-info/RECORD
