Metadata-Version: 2.4
Name: nous
Version: 0.5.1
Summary: Nous: A Neuro-Symbolic Library for Interpretable AI
Author-email: Islam Tlupov <tlupovislam@gmail.com>
License: MIT License
Project-URL: Repository, https://github.com/EmotionEngineer/nous
Classifier: Development Status :: 4 - Beta
Classifier: Intended Audience :: Developers
Classifier: Intended Audience :: Science/Research
Classifier: License :: OSI Approved :: MIT License
Classifier: Programming Language :: Python :: 3
Classifier: Programming Language :: Python :: 3 :: Only
Classifier: Topic :: Scientific/Engineering :: Artificial Intelligence
Classifier: Topic :: Software Development :: Libraries :: Python Modules
Classifier: Typing :: Typed
Requires-Python: >=3.8
License-File: LICENSE
Requires-Dist: torch>=2.1
Requires-Dist: numpy>=1.22
Requires-Dist: pandas>=1.5
Requires-Dist: scikit-learn>=1.2
Provides-Extra: dev
Requires-Dist: pytest>=7.0; extra == "dev"
Requires-Dist: pytest-cov>=4.0; extra == "dev"
Requires-Dist: mypy>=1.5; extra == "dev"
Requires-Dist: ruff>=0.5; extra == "dev"
Requires-Dist: black>=23.0; extra == "dev"
Requires-Dist: matplotlib>=3.6; extra == "dev"
Requires-Dist: seaborn>=0.12; extra == "dev"
Requires-Dist: tqdm>=4.65; extra == "dev"
Requires-Dist: ucimlrepo>=0.0.5; extra == "dev"
Provides-Extra: examples
Requires-Dist: matplotlib>=3.6; extra == "examples"
Requires-Dist: seaborn>=0.12; extra == "examples"
Requires-Dist: tqdm>=4.65; extra == "examples"
Requires-Dist: ucimlrepo>=0.0.5; extra == "examples"
Dynamic: license-file
